eclipse_pytorch/__init__.py
eclipse_pytorch/_nbdev.py
eclipse_pytorch/imports.py
eclipse_pytorch/layers.py
eclipse_pytorch/model.py
eclipse_pytorch-0.0.8.dist-info/LICENSE
eclipse_pytorch-0.0.8.dist-info/METADATA
eclipse_pytorch-0.0.8.dist-info/WHEEL
eclipse_pytorch-0.0.8.dist-info/entry_points.txt
eclipse_pytorch-0.0.8.dist-info/top_level.txt
eclipse_pytorch-0.0.8.dist-info/RECORD
