Metadata-Version: 2.1
Name: eclipse-pytorch
Version: 0.0.8
Summary: A pytorch implementation of Eclipse
Home-page: https://github.com/tcapelle/eclipse_pytorch/tree/master/
Author: Thomas Capelle
Author-email: tcapelle@pm.me
License: Apache Software License 2.0
Keywords: pytorch nowcasting solar energy
Platform: UNKNOWN
Classifier: Development Status :: 3 - Alpha
Classifier: Intended Audience :: Developers
Classifier: Natural Language :: English
Classifier: Programming Language :: Python :: 3.8
Classifier: License :: OSI Approved :: Apache Software License
Requires-Python: >=3.8
Requires-Dist: pip
Requires-Dist: packaging
Requires-Dist: torch (>1.6)
Requires-Dist: fastcore
Provides-Extra: dev
